{"APIRequestInfo":{"ProviderVersion":"CONCORD.R3.1878K.209614","ProviderIdentity":"NBL-USE2-P-APP","ProviderID":"85dca31b7899f944ad0236f5f856af0c","Module":"PackageExtractor","APIVersion":"v1.0","Resource":"Extract","IsLoggedIn":false,"Parameters":{"Package":"2KXJ8ZSAKD58D","PackageFields":"SystemIdentifier,Title,new.Context,CoreField.IIIFResourceType,MediaEncryptedIdentifier,MaxHeight,MaxWidth","RepresentativeFields":"SystemIdentifier,MediaEncryptedIdentifier,Title,MaxWidth,MaxHeight,CoreField.IIIFResourceType","ContentFields":"SystemIdentifier,MediaEncryptedIdentifier,Title,CoreField.IIIFResourceType,MaxWidth,MaxHeight,MediaType,CoreField.Representative_Image_RecordID"},"Status":"Anonymous","UserLogin":"anonymous","Session":"No session (production configuration)","TimeoutPeriodMinutes":20},"APIResponse":{"SystemIdentifier":"NL11L2E9","Title":"Bicycling","new.Context":"Vintage bicycle postcards","CoreField.IIIFResourceType":"Manifest","MediaEncryptedIdentifier":"2KXJ8ZSAKD58D","MaxHeight":"","MaxWidth":"","Representative":{"SystemIdentifier":"NL1BV62","MediaEncryptedIdentifier":"2KXJ8ZY03JHF","Title":"Hut ab! Express!","MaxWidth":"2738","MaxHeight":"4089","CoreField.IIIFResourceType":""},"Content":[{"SystemIdentifier":"NL113C6T","MediaEncryptedIdentifier":"2KXJ8ZPW7U47","Title":"Maxim fahrrader","CoreField.IIIFResourceType":"Manifest","MaxWidth":"","MaxHeight":"","MediaType":"Album","CoreField.Representative_Image_RecordID":"NL1DO000000420585"},{"SystemIdentifier":"NL113C51","MediaEncryptedIdentifier":"2KXJ8ZPWMNU2","Title":"Campionnats du mone","CoreField.IIIFResourceType":"Manifest","MaxWidth":"","MaxHeight":"","MediaType":"Album","CoreField.Representative_Image_RecordID":"NL1DO000000420456"},{"SystemIdentifier":"NL113C55","MediaEncryptedIdentifier":"2KXJ8ZPWMRYB","Title":"Cycles Bercley sur pneus englebert","CoreField.IIIFResourceType":"Manifest","MaxWidth":"","MaxHeight":"","MediaType":"Album","CoreField.Representative_Image_RecordID":"NL1DO000000420460"},{"SystemIdentifier":"NL113C5O","MediaEncryptedIdentifier":"2KXJ8ZPWMQZ4","Title":"La francaise diamant","CoreField.IIIFResourceType":"Manifest","MaxWidth":"","MaxHeight":"","MediaType":"Album","CoreField.Representative_Image_RecordID":"NL1DO000000420499"},{"SystemIdentifier":"NL113C69","MediaEncryptedIdentifier":"2KXJ8ZPWU4X9","Title":"Poulain champion du monde","CoreField.IIIFResourceType":"Manifest","MaxWidth":"","MaxHeight":"","MediaType":"Album","CoreField.Representative_Image_RecordID":"NL1DO000000420542"},{"SystemIdentifier":"NL113C6Q","MediaEncryptedIdentifier":"2KXJ8ZPWUP2X","Title":"Oh, boy!","CoreField.IIIFResourceType":"Manifest","MaxWidth":"","MaxHeight":"","MediaType":"Album","CoreField.Representative_Image_RecordID":"NL1DO000000420576"},{"SystemIdentifier":"NL113C71","MediaEncryptedIdentifier":"2KXJ8ZPW78QR","Title":"I\u0027ll be in to see you on the","CoreField.IIIFResourceType":"Manifest","MaxWidth":"","MaxHeight":"","MediaType":"Album","CoreField.Representative_Image_RecordID":"NL1DO000000420607"},{"SystemIdentifier":"NL113C70","MediaEncryptedIdentifier":"2KXJ8ZPW76ZO","Title":"Cycles et automobiles legia","CoreField.IIIFResourceType":"Manifest","MaxWidth":"","MaxHeight":"","MediaType":"Album","CoreField.Representative_Image_RecordID":"NL1DO000000420602"},{"SystemIdentifier":"NL113C76","MediaEncryptedIdentifier":"2KXJ8ZPW73H8","Title":"Adler","CoreField.IIIFResourceType":"Manifest","MaxWidth":"","MaxHeight":"","MediaType":"Album","CoreField.Representative_Image_RecordID":"NL1DO000000420612"},{"SystemIdentifier":"NL113C7P","MediaEncryptedIdentifier":"2KXJ8ZPW7259","Title":"Die entwickelungsgeschichte des Radlers","CoreField.IIIFResourceType":"Manifest","MaxWidth":"","MaxHeight":"","MediaType":"Album","CoreField.Representative_Image_RecordID":"NL1DO000000420666"},{"SystemIdentifier":"NL113C7V","MediaEncryptedIdentifier":"2KXJ8ZPWVRNB","Title":"Hut ab! Express!","CoreField.IIIFResourceType":"Manifest","MaxWidth":"","MaxHeight":"","MediaType":"Album","CoreField.Representative_Image_RecordID":"NL1DO000000420679"},{"SystemIdentifier":"NL113C80","MediaEncryptedIdentifier":"2KXJ8ZPWV8FR","Title":"Freno carloni","CoreField.IIIFResourceType":"Manifest","MaxWidth":"","MaxHeight":"","MediaType":"Album","CoreField.Representative_Image_RecordID":"NL1DO000000420685"},{"SystemIdentifier":"NL113C8J","MediaEncryptedIdentifier":"2KXJ8ZPWVD0W","Title":"Francesco Gattini","CoreField.IIIFResourceType":"Manifest","MaxWidth":"","MaxHeight":"","MediaType":"Album","CoreField.Representative_Image_RecordID":"NL1DO000000420727"},{"SystemIdentifier":"NL113C8R","MediaEncryptedIdentifier":"2KXJ8ZPWVZ1P","Title":"L\u0027ideal du touriste","CoreField.IIIFResourceType":"Manifest","MaxWidth":"","MaxHeight":"","MediaType":"Album","CoreField.Representative_Image_RecordID":"NL1DO000000420743"},{"SystemIdentifier":"NL113CEW","MediaEncryptedIdentifier":"2KXJ8ZPW9P1X","Title":"Look before you leap","CoreField.IIIFResourceType":"Manifest","MaxWidth":"","MaxHeight":"","MediaType":"Album","CoreField.Representative_Image_RecordID":"NL1DO000000421178"},{"SystemIdentifier":"NL113CDB","MediaEncryptedIdentifier":"2KXJ8ZPWCBAI","Title":"Presentation","CoreField.IIIFResourceType":"Manifest","MaxWidth":"","MaxHeight":"","MediaType":"Album","CoreField.Representative_Image_RecordID":"NL1DO000000421067"},{"SystemIdentifier":"NL11BU45","MediaEncryptedIdentifier":"2KXJ8ZSUQ1N69","Title":"Woman riding bicycle","CoreField.IIIFResourceType":"Manifest","MaxWidth":"","MaxHeight":"","MediaType":"Album","CoreField.Representative_Image_RecordID":"NL1DO000001739069"},{"SystemIdentifier":"NL11BUWR","MediaEncryptedIdentifier":"2KXJ8ZSUKB92P","Title":"Tous les as sur Bicyclette Gurtner","CoreField.IIIFResourceType":"Manifest","MaxWidth":"","MaxHeight":"","MediaType":"Album","CoreField.Representative_Image_RecordID":"NL1DO000001741949"},{"SystemIdentifier":"NL11BVOS","MediaEncryptedIdentifier":"2KXJ8ZSUR35C7","Title":"Woman in hat riding bicycle","CoreField.IIIFResourceType":"Manifest","MaxWidth":"","MaxHeight":"","MediaType":"Album","CoreField.Representative_Image_RecordID":"NL1DO000001745009"},{"SystemIdentifier":"NL112V0Y","MediaEncryptedIdentifier":"2KXJ8ZPG269F","Title":"Bryan L. Bossier postcard collection, 1880s-1920s [000510_01]","CoreField.IIIFResourceType":"Manifest","MaxWidth":"","MaxHeight":"","MediaType":"Album","CoreField.Representative_Image_RecordID":"NL1DO000000130587"},{"SystemIdentifier":"NL113C7U","MediaEncryptedIdentifier":"2KXJ8ZPWVN82","Title":"Hans Langoor gaat uit fietsen","CoreField.IIIFResourceType":"Manifest","MaxWidth":"","MaxHeight":"","MediaType":"Album","CoreField.Representative_Image_RecordID":"NL1DO000000420674"},{"SystemIdentifier":"NL113C83","MediaEncryptedIdentifier":"2KXJ8ZPWVAX2","Title":"All heil!","CoreField.IIIFResourceType":"Manifest","MaxWidth":"","MaxHeight":"","MediaType":"Album","CoreField.Representative_Image_RecordID":"NL1DO000000420694"},{"SystemIdentifier":"NL113C86","MediaEncryptedIdentifier":"2KXJ8ZPWVOGI","Title":"Merry Chirstmas","CoreField.IIIFResourceType":"Manifest","MaxWidth":"","MaxHeight":"","MediaType":"Album","CoreField.Representative_Image_RecordID":"NL1DO000000420700"},{"SystemIdentifier":"NL113C8M","MediaEncryptedIdentifier":"2KXJ8ZPWV4Z9","Title":"Cycles de dion-bouton","CoreField.IIIFResourceType":"Manifest","MaxWidth":"","MaxHeight":"","MediaType":"Album","CoreField.Representative_Image_RecordID":"NL1DO000000420731"},{"SystemIdentifier":"NL113C8Q","MediaEncryptedIdentifier":"2KXJ8ZPWVC9O","Title":"Giraffe riding a bike","CoreField.IIIFResourceType":"Manifest","MaxWidth":"","MaxHeight":"","MediaType":"Album","CoreField.Representative_Image_RecordID":"NL1DO000000420738"},{"SystemIdentifier":"NL113C9C","MediaEncryptedIdentifier":"2KXJ8ZPWOAH2","Title":"Pig riding a bike","CoreField.IIIFResourceType":"Manifest","MaxWidth":"","MaxHeight":"","MediaType":"Album","CoreField.Representative_Image_RecordID":"NL1DO000000420786"},{"SystemIdentifier":"NL113C9O","MediaEncryptedIdentifier":"2KXJ8ZPWOS0D","Title":"Cats riding bikes","CoreField.IIIFResourceType":"Manifest","MaxWidth":"","MaxHeight":"","MediaType":"Album","CoreField.Representative_Image_RecordID":"NL1DO000000420806"},{"SystemIdentifier":"NL113C9Z","MediaEncryptedIdentifier":"2KXJ8ZPW68YR","Title":"Nous acconrous troupe joyeuse vous apportant l\u0027annee henieuse","CoreField.IIIFResourceType":"Manifest","MaxWidth":"","MaxHeight":"","MediaType":"Album","CoreField.Representative_Image_RecordID":"NL1DO000000420825"},{"SystemIdentifier":"NL113CAL","MediaEncryptedIdentifier":"2KXJ8ZPW6IHU","Title":"Cats riding bikes","CoreField.IIIFResourceType":"Manifest","MaxWidth":"","MaxHeight":"","MediaType":"Album","CoreField.Representative_Image_RecordID":"NL1DO000000420869"},{"SystemIdentifier":"NL113CB6","MediaEncryptedIdentifier":"2KXJ8ZPW8CEO","Title":"Ateliers joe bridge","CoreField.IIIFResourceType":"Manifest","MaxWidth":"","MaxHeight":"","MediaType":"Album","CoreField.Representative_Image_RecordID":"NL1DO000000420918"},{"SystemIdentifier":"NL113CBH","MediaEncryptedIdentifier":"2KXJ8ZPW8KI7","Title":"Williams\u0027s famous toffees","CoreField.IIIFResourceType":"Manifest","MaxWidth":"","MaxHeight":"","MediaType":"Album","CoreField.Representative_Image_RecordID":"NL1DO000000420939"},{"SystemIdentifier":"NL113CCN","MediaEncryptedIdentifier":"2KXJ8ZPWYX0R","Title":"All Heil!","CoreField.IIIFResourceType":"Manifest","MaxWidth":"","MaxHeight":"","MediaType":"Album","CoreField.Representative_Image_RecordID":"NL1DO000000421008"},{"SystemIdentifier":"NL113CFO","MediaEncryptedIdentifier":"2KXJ8ZPW9CGO","Title":"All Heil","CoreField.IIIFResourceType":"Manifest","MaxWidth":"","MaxHeight":"","MediaType":"Album","CoreField.Representative_Image_RecordID":"NL1DO000000421241"},{"SystemIdentifier":"NL113CFP","MediaEncryptedIdentifier":"2KXJ8ZPW9O8I","Title":"Woman riding a bike","CoreField.IIIFResourceType":"Manifest","MaxWidth":"","MaxHeight":"","MediaType":"Album","CoreField.Representative_Image_RecordID":"NL1DO000000421244"},{"SystemIdentifier":"NL113CGO","MediaEncryptedIdentifier":"2KXJ8ZPWJP3X","Title":"Notice: Agiter la carte d\u0027un rapide mouvement circulaire et vous verrez tourueu les roues de tandem","CoreField.IIIFResourceType":"Manifest","MaxWidth":"","MaxHeight":"","MediaType":"Album","CoreField.Representative_Image_RecordID":"NL1DO000000421311"},{"SystemIdentifier":"NL113CHS","MediaEncryptedIdentifier":"2KXJ8ZPW2OUI","Title":"GruB Vom Krampus!","CoreField.IIIFResourceType":"Manifest","MaxWidth":"","MaxHeight":"","MediaType":"Album","CoreField.Representative_Image_RecordID":"NL1DO000000421403"},{"SystemIdentifier":"NL113CI3","MediaEncryptedIdentifier":"2KXJ8ZPW275X","Title":"Man and woman riding bikes","CoreField.IIIFResourceType":"Manifest","MaxWidth":"","MaxHeight":"","MediaType":"Album","CoreField.Representative_Image_RecordID":"NL1DO000000421415"},{"SystemIdentifier":"NL113CMA","MediaEncryptedIdentifier":"2KXJ8ZPWFY5Q","Title":"Les adieux d\u0027un pneun en 1916","CoreField.IIIFResourceType":"Manifest","MaxWidth":"","MaxHeight":"","MediaType":"Album","CoreField.Representative_Image_RecordID":"NL1DO000000421723"},{"SystemIdentifier":"NL113CMY","MediaEncryptedIdentifier":"2KXJ8ZPW0EUQ","Title":"Man riding a bike with a bull","CoreField.IIIFResourceType":"Manifest","MaxWidth":"","MaxHeight":"","MediaType":"Album","CoreField.Representative_Image_RecordID":"NL1DO000000421767"},{"SystemIdentifier":"NL113CNW","MediaEncryptedIdentifier":"2KXJ8ZPWKMT1","Title":"I\u0027m coming love to thee","CoreField.IIIFResourceType":"Manifest","MaxWidth":"","MaxHeight":"","MediaType":"Album","CoreField.Representative_Image_RecordID":"NL1DO000000421833"},{"SystemIdentifier":"NL113C7K","MediaEncryptedIdentifier":"2KXJ8ZPW75OU","Title":"Frohliche ostern!","CoreField.IIIFResourceType":"Manifest","MaxWidth":"","MaxHeight":"","MediaType":"Album","CoreField.Representative_Image_RecordID":"NL1DO000000420652"},{"SystemIdentifier":"NL11BS8F","MediaEncryptedIdentifier":"2KXJ8ZSUHSE63","Title":"Man on bicycle and woman on horse","CoreField.IIIFResourceType":"Manifest","MaxWidth":"","MaxHeight":"","MediaType":"Album","CoreField.Representative_Image_RecordID":"NL1DO000001732510"}],"useremail":""}}